datasette_json_html/__init__.py
datasette_json_html-1.0.1.dist-info/LICENSE
datasette_json_html-1.0.1.dist-info/METADATA
datasette_json_html-1.0.1.dist-info/WHEEL
datasette_json_html-1.0.1.dist-info/entry_points.txt
datasette_json_html-1.0.1.dist-info/top_level.txt
datasette_json_html-1.0.1.dist-info/RECORD
