Metadata-Version: 2.1
Name: datasette-json-html
Version: 1.0.1
Summary: Datasette plugin for rendering HTML based on JSON values
Home-page: https://datasette.io/plugins/datasette-json-html
Author: Simon Willison
License: Apache License, Version 2.0
Project-URL: Issues, https://github.com/simonw/datasette-json-html/issues
Project-URL: CI, https://github.com/simonw/datasette-json-html/actions
Project-URL: Changelog, https://github.com/simonw/datasette-json-html/releases
Platform: UNKNOWN
Requires-Dist: datasette
Provides-Extra: test
Requires-Dist: pytest ; extra == 'test'
Requires-Dist: pytest-asyncio ; extra == 'test'
Requires-Dist: httpx ; extra == 'test'
